{
  "rooms": [
    {
      "RoomName": "Eletronica",
      "Capacity": 10,
      "id": 1,
      "hosts": []
    },

    {
      "RoomName": "Comunicação",
      "Capacity": 5,
      "id": 2,
      "hosts": []
    },

    {
      "RoomName": "Medecina",
      "Capacity": 5,
      "id": 3,
      "hosts": []
    },

    {
      "RoomName": "Programação",
      "Capacity": 20,
      "id": 4,
      "hosts": []
    },

    {
      "RoomName": "Redes",
      "Capacity": 10,
      "id": 5,
      "hosts": []
    },

    {
      "RoomName": "Sistemas",
      "Capacity": 5,
      "id": 6,
      "hosts": []
    },

    {
      "RoomName": "Base de Dados",
      "Capacity": 20,
      "id": 7,
      "hosts": []
    }
  ]
}
